{"skeleton":{"hash":"CsFw8AT8GKZ+oIqa0MXHng5bvkY","spine":"2.1.27","width":421.77,"height":230.49,"images":"C:\\Users\\אוהד רז\\Downloads\\Darkest Dungeon Animation Unpacking\\Heroes\\Crusader\\fx\\holy_lance"},"bones":[{"name":"root"},{"name":"fxskill","parent":"root"},{"name":"arm_glow","parent":"fxskill","x":17.16,"y":138.06},{"name":"ghost","parent":"fxskill","x":17,"y":138.31},{"name":"rim_light","parent":"fxskill","x":36.48,"y":136.68},{"name":"shadow","parent":"fxskill","x":-101.29,"y":116.43},{"name":"ghost_rim_light","parent":"ghost","x":19.48,"y":-1.62}],"slots":[{"name":"attack_charge","bone":"root"},{"name":"ghost","bone":"ghost","attachment":"ghost"},{"name":"ghost_rim_light","bone":"ghost_rim_light","attachment":"ghost_rim_light"},{"name":"arm_glow","bone":"arm_glow","attachment":"arm_glow"},{"name":"shadow","bone":"shadow","attachment":"shadow"},{"name":"rim_light","bone":"rim_light","attachment":"rim_light"}],"skins":{"default":{"arm_glow":{"arm_glow":{"type":"mesh","uvs":[0,0,0.33333,0,0.66666,0,1,0,1,0.33333,1,0.66666,1,1,0.66666,1,0.33333,1,0,1,0,0.66666,0,0.33333,0.33333,0.33333,0.33333,0.66666,0.66666,0.33333,0.66666,0.66666],"triangles":[11,0,1,12,1,2,11,1,12,14,2,3,12,2,14,14,3,4,10,11,12,13,12,14,10,12,13,15,14,4,13,14,15,15,4,5,9,10,13,8,13,15,9,13,8,7,15,5,8,15,7,7,5,6],"vertices":[-192,93,-64,93,63.99,93,191.99,93,191.99,31,191.99,-30.99,191.99,-92.99,63.99,-92.99,-64,-92.99,-192,-92.99,-192,-30.99,-192,31,-64,31,-64,-30.99,63.99,31,63.99,-30.99],"hull":12,"edges":[0,22,0,2,2,4,4,6,6,8,8,10,10,12,12,14,14,16,16,18,18,20,20,22],"width":768,"height":372}},"ghost":{"ghost":{"type":"mesh","uvs":[0,0,0.33333,0,0.66666,0,1,0,1,0.33333,1,0.66666,1,1,0.66666,1,0.33333,1,0,1,0,0.66666,0,0.33333,0.33333,0.33333,0.33333,0.66666,0.66666,0.33333,0.66666,0.66666],"triangles":[11,0,1,12,1,2,11,1,12,14,2,3,12,2,14,14,3,4,10,11,12,13,12,14,10,12,13,15,14,4,13,14,15,15,4,5,9,10,13,8,13,15,9,13,8,7,15,5,8,15,7,7,5,6],"vertices":[-189,91.75,-63,91.75,62.99,91.75,189,91.75,189,30.58,189,-30.58,189,-91.74,62.99,-91.74,-63,-91.74,-189,-91.74,-189,-30.58,-189,30.58,-63,30.58,-63,-30.58,62.99,30.58,62.99,-30.58],"hull":12,"edges":[0,22,0,2,2,4,4,6,6,8,8,10,10,12,12,14,14,16,16,18,18,20,20,22],"width":756,"height":367}},"ghost_rim_light":{"ghost_rim_light":{"type":"mesh","uvs":[0,0,0.33333,0,0.66666,0,1,0,1,0.33333,1,0.66666,1,1,0.66666,1,0.33333,1,0,1,0,0.66666,0,0.33333,0.33333,0.33333,0.33333,0.66666,0.66666,0.33333,0.66666,0.66666],"triangles":[11,0,1,12,1,2,11,1,12,14,2,3,12,2,14,14,3,4,10,11,12,13,12,14,10,12,13,15,14,4,13,14,15,15,4,5,9,10,13,8,13,15,9,13,8,7,15,5,8,15,7,7,5,6],"vertices":[-176.75,88.25,-58.91,88.25,58.91,88.25,176.74,88.25,176.74,29.41,176.74,-29.41,176.74,-88.24,58.91,-88.24,-58.91,-88.24,-176.75,-88.24,-176.75,-29.41,-176.75,29.41,-58.91,29.41,-58.91,-29.41,58.91,29.41,58.91,-29.41],"hull":12,"edges":[0,22,0,2,2,4,4,6,6,8,8,10,10,12,12,14,14,16,16,18,18,20,20,22],"width":707,"height":353}},"rim_light":{"rim_light":{"type":"mesh","uvs":[0,0,0.33333,0,0.66666,0,1,0,1,0.33333,1,0.66666,1,1,0.66666,1,0.33333,1,0,1,0,0.66666,0,0.33333,0.33333,0.33333,0.33333,0.66666,0.66666,0.33333,0.66666,0.66666],"triangles":[11,0,1,12,1,2,11,1,12,14,2,3,12,2,14,14,3,4,10,11,12,13,12,14,10,12,13,15,14,4,13,14,15,15,4,5,9,10,13,8,13,15,9,13,8,7,15,5,8,15,7,7,5,6],"vertices":[-176.75,88.25,-58.91,88.25,58.91,88.25,176.74,88.25,176.74,29.41,176.74,-29.41,176.74,-88.24,58.91,-88.24,-58.91,-88.24,-176.75,-88.24,-176.75,-29.41,-176.75,29.41,-58.91,29.41,-58.91,-29.41,58.91,29.41,58.91,-29.41],"hull":12,"edges":[0,22,0,2,2,4,4,6,6,8,8,10,10,12,12,14,14,16,16,18,18,20,20,22],"width":707,"height":353}},"shadow":{"shadow":{"type":"mesh","uvs":[0,0,0.5,0,1,0,1,0.5,1,1,0.5,1,0,1,0,0.5,0.5,0.5],"triangles":[7,0,1,8,1,2,7,1,8,8,2,3,6,7,8,5,8,3,6,8,5,5,3,4],"vertices":[-107.25,115.25,0,115.25,107.25,115.25,107.25,0,107.25,-115.24,0,-115.24,-107.25,-115.24,-107.25,0,0,0],"hull":8,"edges":[0,14,0,2,2,4,4,6,6,8,8,10,10,12,12,14],"width":429,"height":461}}}},"animations":{"holy_lance":{"slots":{"arm_glow":{"color":[{"time":0,"color":"ffffff00","curve":[0.25,-0.72,0.75,1]},{"time":0.1333,"color":"ffffffff","curve":"stepped"},{"time":0.6,"color":"ffffffff","curve":[0.327,0,0.838,0.71]},{"time":1.3,"color":"ffffff00","curve":"stepped"},{"time":1.8666,"color":"ffffff00"}]},"ghost":{"color":[{"time":0,"color":"ffffff00","curve":[0.25,-0.72,0.75,1]},{"time":0.1,"color":"ffffffff","curve":"stepped"},{"time":0.6,"color":"ffffffff","curve":[0.327,0,0.838,0.71]},{"time":1.1666,"color":"ffffff00","curve":"stepped"},{"time":1.8666,"color":"ffffff00"}]},"ghost_rim_light":{"color":[{"time":0,"color":"ffffff00","curve":[0.25,-0.72,0.75,1]},{"time":0.1,"color":"ffffffff","curve":"stepped"},{"time":0.6,"color":"ffffffff","curve":[0.327,0,0.838,0.71]},{"time":1.1666,"color":"ffffff00","curve":"stepped"},{"time":1.8666,"color":"ffffff00"}]},"rim_light":{"color":[{"time":0,"color":"ffffff00","curve":[0.25,-0.72,0.75,1]},{"time":0.1,"color":"ffffffff","curve":"stepped"},{"time":0.6,"color":"ffffffff","curve":[0.327,0,0.838,0.71]},{"time":1.3333,"color":"ffffff00","curve":"stepped"},{"time":1.8666,"color":"ffffff00"}]},"shadow":{"color":[{"time":0,"color":"ffffff00","curve":[0.25,-0.72,0.75,1]},{"time":0.1666,"color":"ffffffff","curve":"stepped"},{"time":0.6,"color":"ffffffff","curve":[0.327,0,0.838,0.71]},{"time":1.2666,"color":"ffffff00","curve":"stepped"},{"time":1.8666,"color":"ffffff00"}]}},"bones":{"ghost":{"translate":[{"time":0,"x":0,"y":0,"curve":[0.277,-0.43,0.75,1]},{"time":0.1333,"x":54.69,"y":0},{"time":1.8666,"x":80.24,"y":0}]}}}}}